qbit/__init__.py
qbit/gate.py
qbit/pauli_group.py
qbit/qbit.py
pyqbit-0.2.2.dist-info/LICENSE
pyqbit-0.2.2.dist-info/METADATA
pyqbit-0.2.2.dist-info/WHEEL
pyqbit-0.2.2.dist-info/top_level.txt
pyqbit-0.2.2.dist-info/RECORD
