Metadata-Version: 2.1
Name: pyqbit
Version: 0.2.2
Summary: Quantum bit and the usual gates in numeric forms straight from the Wikipedia
Home-page: https://github.com/kummahiih/pyqbit
Author: Pauli Rikula
Author-email: UNKNOWN
License: MIT
Platform: UNKNOWN
Classifier: License :: OSI Approved :: MIT License
Classifier: Programming Language :: Python :: 3.6
Requires-Python: ~=3.6
Requires-Dist: numpy (>=1.18.1)
